versification_utils/__init__.py
versification_utils/export.py
versification_utils/mapping.py
versification_utils/sniffing.py
versification_utils/vref.txt
versification_utils/diagnostics/vrs_diffs.yaml
versification_utils/standard_mappings/eng.json
versification_utils/standard_mappings/lxx.json
versification_utils/standard_mappings/org.json
versification_utils/standard_mappings/rsc.json
versification_utils/standard_mappings/rso.json
versification_utils/standard_mappings/vul.json
versification_utils-0.0.1.dist-info/METADATA
versification_utils-0.0.1.dist-info/WHEEL
versification_utils-0.0.1.dist-info/top_level.txt
versification_utils-0.0.1.dist-info/RECORD
