Metadata-Version: 2.1
Name: versification_utils
Version: 0.0.1
Summary: Tools to detect and convert between Bible versifications
Home-page: https://github.com/jcuenod/versification_utils
Author: James Cuénod
Author-email: j3frea+github@gmail.com
License: MIT
Classifier: Programming Language :: Python :: 3
Classifier: License :: OSI Approved :: MIT License
Classifier: Operating System :: OS Independent
Requires-Python: >=3.8
